dl_utils/__init__.py
dl_utils/label_funcs.py
dl_utils/misc.py
dl_utils/nns.py
dl_utils/probs.py
dl_utils/tensor_funcs.py
dl_utils/torch_misc.py
dl_utils/vision_dsets.py
dl_utils385-0.12.8.dist-info/LICENSE
dl_utils385-0.12.8.dist-info/METADATA
dl_utils385-0.12.8.dist-info/WHEEL
dl_utils385-0.12.8.dist-info/top_level.txt
dl_utils385-0.12.8.dist-info/RECORD
