Metadata-Version: 2.1
Name: dl_utils385
Version: 0.12.8
Summary: Useful code for deep learning projects
Home-page: https://github.com/Lou1sM/dl_utils
Author: Louis Mahon
Author-email: lmahonology@gmail.com
Classifier: Programming Language :: Python :: 3
Classifier: License :: OSI Approved :: MIT License
Classifier: Operating System :: OS Independent
Requires-Python: >=3.6
License-File: LICENSE
Requires-Dist: numpy
Requires-Dist: scikit-learn
